libpastis/__init__.py
libpastis/agent.py
libpastis/enginedesc.py
libpastis/package.py
libpastis/sast.py
libpastis/types.py
libpastis/utils.py
libpastis/proto/__init__.py
libpastis/proto/message_pb2.py
pastis_framework-1.0.13.data/scripts/pastis-benchmark
pastis_framework-1.0.13.data/scripts/pastis-broker
pastis_framework-1.0.13.data/scripts/pastisd
pastisaflpp/__init__.py
pastisaflpp/__main__.py
pastisaflpp/addon.py
pastisaflpp/aflpp.py
pastisaflpp/driver.py
pastisaflpp/replay.py
pastisaflpp/workspace.py
pastisbenchmark/__init__.py
pastisbenchmark/models.py
pastisbenchmark/plotter.py
pastisbenchmark/replayer.py
pastisbenchmark/results.py
pastisbroker/__init__.py
pastisbroker/broker.py
pastisbroker/client.py
pastisbroker/coverage.py
pastisbroker/dashboard.py
pastisbroker/stat_manager.py
pastisbroker/utils.py
pastisbroker/workspace.py
pastishonggfuzz/__init__.py
pastishonggfuzz/__main__.py
pastishonggfuzz/addon.py
pastishonggfuzz/driver.py
pastishonggfuzz/honggfuzz.py
pastishonggfuzz/replay.py
pastishonggfuzz/workspace.py
pastistritondse/__init__.py
pastistritondse/__main__.py
pastistritondse/addon.py
pastistritondse/driver.py
pastis_framework-1.0.13.dist-info/LICENSE
pastis_framework-1.0.13.dist-info/METADATA
pastis_framework-1.0.13.dist-info/WHEEL
pastis_framework-1.0.13.dist-info/entry_points.txt
pastis_framework-1.0.13.dist-info/top_level.txt
pastis_framework-1.0.13.dist-info/RECORD
