Metadata-Version: 2.1
Name: pastis-framework
Version: 1.0.13
Summary: PASTIS framework for collaborative fuzzing
Home-page: https://github.com/quarkslab/pastis
Author: Quarkslab
License: AGPL-3.0
Project-URL: Documentation, https://quarkslab.github.io/pastis/
Project-URL: Bug Tracker, https://github.com/quarkslab/pastis/issues
Project-URL: Source, https://github.com/quarkslab/pastis
Classifier: Topic :: Security
Classifier: Environment :: Console
Classifier: Operating System :: OS Independent
Requires-Python: >=3.9
License-File: LICENSE
Requires-Dist: protobuf
Requires-Dist: pyzmq
Requires-Dist: psutil
Requires-Dist: aenum
Requires-Dist: lief>=v0.15.0
Requires-Dist: python-magic
Requires-Dist: click
Requires-Dist: coloredlogs
Requires-Dist: quokka-project
Requires-Dist: watchdog
Requires-Dist: pydantic
Requires-Dist: matplotlib
Requires-Dist: joblib
Requires-Dist: rich
Requires-Dist: tritondse>=v0.1.12
